{
    "success": true,
    "data": [
        {
            "DT": 1637305200000,
            "Open": "5058000",
            "Low": "5022000",
            "High": "5070000",
            "Close": "5050000",
            "Volume": "541.8281",
            "Adj_Close":s "5050000"
        },
        {
            "DT": 1637308800000,
            "Open": "5049000",
            "Low": "5048000",
            "High": "5178000",
            "Close": "5150000",
            "Volume": "565.2713",
            "Adj_Close": "5150000"
        },
        {
            "DT": 1637312400000,
            "Open": "5152000",
            "Low": "5148000",
            "High": "5201000",
            "Close": "5166000",
            "Volume": "446.9698",
            "Adj_Close": "5166000"
        },
        {
            "DT": 1637316000000,
            "Open": "5166000",
            "Low": "5134000",
            "High": "5172000",
            "Close": "5156000",
            "Volume": "258.645",
            "Adj_Close": "5156000"
        },
        {
            "DT": 1637319600000,
            "Open": "5157000",
            "Low": "5135000",
            "High": "5172000",
            "Close": "5159000",
            "Volume": "345.3499",
            "Adj_Close": "5159000"
        },
        {
            "DT": 1637323200000,
            "Open": "5160000",
            "Low": "5155000",
            "High": "5194000",
            "Close": "5164000",
            "Volume": "345.6156",
            "Adj_Close": "5164000"
        },
        {
            "DT": 1637326800000,
            "Open": "5165000",
            "Low": "5162000",
            "High": "5233000",
            "Close": "5229000",
            "Volume": "439.5503",
            "Adj_Close": "5229000"
        },
        {
            "DT": 1637330400000,
            "Open": "5231000",
            "Low": "5213000",
            "High": "5259000",
            "Close": "5255000",
            "Volume": "561.9586",
            "Adj_Close": "5255000"
        },
        {
            "DT": 1637334000000,
            "Open": "5255000",
            "Low": "5227000",
            "High": "5260000",
            "Close": "5238000",
            "Volume": "334.9863",
            "Adj_Close": "5238000"
        },
        {
            "DT": 1637337600000,
            "Open": "5239000",
            "Low": "5226000",
            "High": "5261000",
            "Close": "5255000",
            "Volume": "287.435",
            "Adj_Close": "5255000"
        },
        {
            "DT": 1637341200000,
            "Open": "5257000",
            "Low": "5254000",
            "High": "5281000",
            "Close": "5267000",
            "Volume": "182.8768",
            "Adj_Close": "5267000"
        },
        {
            "DT": 1637344800000,
            "Open": "5267000",
            "Low": "5256000",
            "High": "5282000",
            "Close": "5282000",
            "Volume": "149.0411",
            "Adj_Close": "5282000"
        },
        {
            "DT": 1637348400000,
            "Open": "5283000",
            "Low": "5271000",
            "High": "5314000",
            "Close": "5310000",
            "Volume": "162.4239",
            "Adj_Close": "5310000"
        },
        {
            "DT": 1637352000000,
            "Open": "5309000",
            "Low": "5285000",
            "High": "5330000",
            "Close": "5290000",
            "Volume": "333.9798",
            "Adj_Close": "5290000"
        },
        {
            "DT": 1637355600000,
            "Open": "5290000",
            "Low": "5271000",
            "High": "5292000",
            "Close": "5292000",
            "Volume": "144.9129",
            "Adj_Close": "5292000"
        },
        {
            "DT": 1637359200000,
            "Open": "5293000",
            "Low": "5288000",
            "High": "5320000",
            "Close": "5295000",
            "Volume": "256.2647",
            "Adj_Close": "5295000"
        },
        {
            "DT": 1637362800000,
            "Open": "5294000",
            "Low": "5285000",
            "High": "5322000",
            "Close": "5307000",
            "Volume": "302.0308",
            "Adj_Close": "5307000"
        },
        {
            "DT": 1637366400000,
            "Open": "5307000",
            "Low": "5289000",
            "High": "5345000",
            "Close": "5316000",
            "Volume": "503.5353",
            "Adj_Close": "5316000"
        },
        {
            "DT": 1637370000000,
            "Open": "5315000",
            "Low": "5314000",
            "High": "5370000",
            "Close": "5368000",
            "Volume": "363.2792",
            "Adj_Close": "5368000"
        },
        {
            "DT": 1637373600000,
            "Open": "5366000",
            "Low": "5343000",
            "High": "5388000",
            "Close": "5343000",
            "Volume": "308.3436",
            "Adj_Close": "5343000"
        },
        {
            "DT": 1637377200000,
            "Open": "5343000",
            "Low": "5297000",
            "High": "5355000",
            "Close": "5304000",
            "Volume": "512.6831",
            "Adj_Close": "5304000"
        },
        {
            "DT": 1637380800000,
            "Open": "5306000",
            "Low": "5283000",
            "High": "5323000",
            "Close": "5322000",
            "Volume": "225.8982",
            "Adj_Close": "5322000"
        },
        {
            "DT": 1637384400000,
            "Open": "5323000",
            "Low": "5301000",
            "High": "5330000",
            "Close": "5310000",
            "Volume": "213.2272",
            "Adj_Close": "5310000"
        },
        {
            "DT": 1637388000000,
            "Open": "5311000",
            "Low": "5305000",
            "High": "5352000",
            "Close": "5329000",
            "Volume": "303.2812",
            "Adj_Close": "5329000"
        },
        {
            "DT": 1637391600000,
            "Open": "5327000",
            "Low": "5305000",
            "High": "5336000",
            "Close": "5312000",
            "Volume": "200.9006",
            "Adj_Close": "5312000"
        },
        {
            "DT": 1637395200000,
            "Open": "5311000",
            "Low": "5295000",
            "High": "5330000",
            "Close": "5313000",
            "Volume": "184.6853",
            "Adj_Close": "5313000"
        },
        {
            "DT": 1637398800000,
            "Open": "5313000",
            "Low": "5305000",
            "High": "5326000",
            "Close": "5315000",
            "Volume": "123.5291",
            "Adj_Close": "5315000"
        },
        {
            "DT": 1637402400000,
            "Open": "5313000",
            "Low": "5303000",
            "High": "5332000",
            "Close": "5310000",
            "Volume": "181.4706",
            "Adj_Close": "5310000"
        },
        {
            "DT": 1637406000000,
            "Open": "5312000",
            "Low": "5311000",
            "High": "5337000",
            "Close": "5331000",
            "Volume": "135.1807",
            "Adj_Close": "5331000"
        },
        {
            "DT": 1637409600000,
            "Open": "5336000",
            "Low": "5333000",
            "High": "5366000",
            "Close": "5344000",
            "Volume": "132.4255",
            "Adj_Close": "5344000"
        },
        {
            "DT": 1637413200000,
            "Open": "5344000",
            "Low": "5316000",
            "High": "5347000",
            "Close": "5322000",
            "Volume": "151.2842",
            "Adj_Close": "5322000"
        },
        {
            "DT": 1637416800000,
            "Open": "5325000",
            "Low": "5315000",
            "High": "5347000",
            "Close": "5315000",
            "Volume": "147.1172",
            "Adj_Close": "5315000"
        },
        {
            "DT": 1637420400000,
            "Open": "5315000",
            "Low": "5232000",
            "High": "5316000",
            "Close": "5232000",
            "Volume": "696.1019",
            "Adj_Close": "5232000"
        },
        {
            "DT": 1637424000000,
            "Open": "5233000",
            "Low": "5229000",
            "High": "5279000",
            "Close": "5279000",
            "Volume": "171.7856",
            "Adj_Close": "5279000"
        },
        {
            "DT": 1637427600000,
            "Open": "5278000",
            "Low": "5263000",
            "High": "5290000",
            "Close": "5290000",
            "Volume": "118.4395",
            "Adj_Close": "5290000"
        },
        {
            "DT": 1637431200000,
            "Open": "5284000",
            "Low": "5283000",
            "High": "5421000",
            "Close": "5396000",
            "Volume": "542.1564",
            "Adj_Close": "5396000"
        },
        {
            "DT": 1637434800000,
            "Open": "5400000",
            "Low": "5394000",
            "High": "5440000",
            "Close": "5438000",
            "Volume": "182.0734",
            "Adj_Close": "5438000"
        },
        {
            "DT": 1637438400000,
            "Open": "5440000",
            "Low": "5433000",
            "High": "5454000",
            "Close": "5451000",
            "Volume": "144.384",
            "Adj_Close": "5451000"
        },
        {
            "DT": 1637442000000,
            "Open": "5452000",
            "Low": "5447000",
            "High": "5479000",
            "Close": "5479000",
            "Volume": "121.071",
            "Adj_Close": "5479000"
        },
        {
            "DT": 1637445600000,
            "Open": "5479000",
            "Low": "5446000",
            "High": "5484000",
            "Close": "5454000",
            "Volume": "213.5694",
            "Adj_Close": "5454000"
        },
        {
            "DT": 1637449200000,
            "Open": "5456000",
            "Low": "5448000",
            "High": "5467000",
            "Close": "5450000",
            "Volume": "151.7817",
            "Adj_Close": "5450000"
        },
        {
            "DT": 1637452800000,
            "Open": "5452000",
            "Low": "5409000",
            "High": "5452000",
            "Close": "5417000",
            "Volume": "445.4188",
            "Adj_Close": "5417000"
        },
        {
            "DT": 1637456400000,
            "Open": "5416000",
            "Low": "5403000",
            "High": "5428000",
            "Close": "5411000",
            "Volume": "194.8289",
            "Adj_Close": "5411000"
        },
        {
            "DT": 1637460000000,
            "Open": "5414000",
            "Low": "5370000",
            "High": "5419000",
            "Close": "5398000",
            "Volume": "302.2383",
            "Adj_Close": "5398000"
        },
        {
            "DT": 1637463600000,
            "Open": "5398000",
            "Low": "5379000",
            "High": "5420000",
            "Close": "5383000",
            "Volume": "239.9041",
            "Adj_Close": "5383000"
        },
        {
            "DT": 1637467200000,
            "Open": "5381000",
            "Low": "5369000",
            "High": "5406000",
            "Close": "5370000",
            "Volume": "378.1027",
            "Adj_Close": "5370000"
        },
        {
            "DT": 1637470800000,
            "Open": "5371000",
            "Low": "5369000",
            "High": "5414000",
            "Close": "5411000",
            "Volume": "232.0208",
            "Adj_Close": "5411000"
        },
        {
            "DT": 1637474400000,
            "Open": "5412000",
            "Low": "5395000",
            "High": "5417000",
            "Close": "5414000",
            "Volume": "372.796",
            "Adj_Close": "5414000"
        },
        {
            "DT": 1637478000000,
            "Open": "5415000",
            "Low": "5390000",
            "High": "5420000",
            "Close": "5390000",
            "Volume": "346.8959",
            "Adj_Close": "5390000"
        },
        {
            "DT": 1637481600000,
            "Open": "5390000",
            "Low": "5372000",
            "High": "5400000",
            "Close": "5376000",
            "Volume": "284.8322",
            "Adj_Close": "5376000"
        },
        {
            "DT": 1637485200000,
            "Open": "5375000",
            "Low": "5370000",
            "High": "5388000",
            "Close": "5380000",
            "Volume": "290.4638",
            "Adj_Close": "5380000"
        },
        {
            "DT": 1637488800000,
            "Open": "5380000",
            "Low": "5354000",
            "High": "5392000",
            "Close": "5365000",
            "Volume": "243.8137",
            "Adj_Close": "5365000"
        },
        {
            "DT": 1637492400000,
            "Open": "5365000",
            "Low": "5350000",
            "High": "5391000",
            "Close": "5356000",
            "Volume": "324.1958",
            "Adj_Close": "5356000"
        },
        {
            "DT": 1637496000000,
            "Open": "5356000",
            "Low": "5350000",
            "High": "5382000",
            "Close": "5366000",
            "Volume": "255.7571",
            "Adj_Close": "5366000"
        },
        {
            "DT": 1637499600000,
            "Open": "5366000",
            "Low": "5365000",
            "High": "5384000",
            "Close": "5369000",
            "Volume": "199.344",
            "Adj_Close": "5369000"
        },
        {
            "DT": 1637503200000,
            "Open": "5369000",
            "Low": "5345000",
            "High": "5379000",
            "Close": "5373000",
            "Volume": "277.502",
            "Adj_Close": "5373000"
        },
        {
            "DT": 1637506800000,
            "Open": "5373000",
            "Low": "5365000",
            "High": "5422000",
            "Close": "5408000",
            "Volume": "206.716",
            "Adj_Close": "5408000"
        },
        {
            "DT": 1637510400000,
            "Open": "5411000",
            "Low": "5383000",
            "High": "5463000",
            "Close": "5455000",
            "Volume": "329.1096",
            "Adj_Close": "5455000"
        },
        {
            "DT": 1637514000000,
            "Open": "5459000",
            "Low": "5410000",
            "High": "5468000",
            "Close": "5414000",
            "Volume": "235.6464",
            "Adj_Close": "5414000"
        },
        {
            "DT": 1637517600000,
            "Open": "5415000",
            "Low": "5394000",
            "High": "5415000",
            "Close": "5403000",
            "Volume": "149.4142",
            "Adj_Close": "5403000"
        },
        {
            "DT": 1637521200000,
            "Open": "5403000",
            "Low": "5380000",
            "High": "5404000",
            "Close": "5380000",
            "Volume": "215.7267",
            "Adj_Close": "5380000"
        },
        {
            "DT": 1637524800000,
            "Open": "5381000",
            "Low": "5375000",
            "High": "5418000",
            "Close": "5413000",
            "Volume": "167.9947",
            "Adj_Close": "5413000"
        },
        {
            "DT": 1637528400000,
            "Open": "5411000",
            "Low": "5388000",
            "High": "5416000",
            "Close": "5388000",
            "Volume": "113.3478",
            "Adj_Close": "5388000"
        },
        {
            "DT": 1637532000000,
            "Open": "5388000",
            "Low": "5336000",
            "High": "5388000",
            "Close": "5349000",
            "Volume": "211.2885",
            "Adj_Close": "5349000"
        },
        {
            "DT": 1637535600000,
            "Open": "5349000",
            "Low": "5290000",
            "High": "5366000",
            "Close": "5301000",
            "Volume": "376.568",
            "Adj_Close": "5301000"
        },
        {
            "DT": 1637539200000,
            "Open": "5304000",
            "Low": "5243000",
            "High": "5311000",
            "Close": "5263000",
            "Volume": "649.9818",
            "Adj_Close": "5263000"
        },
        {
            "DT": 1637542800000,
            "Open": "5262000",
            "Low": "5174000",
            "High": "5270000",
            "Close": "5229000",
            "Volume": "618.6372",
            "Adj_Close": "5229000"
        },
        {
            "DT": 1637546400000,
            "Open": "5227000",
            "Low": "5181000",
            "High": "5237000",
            "Close": "5225000",
            "Volume": "374.9323",
            "Adj_Close": "5225000"
        },
        {
            "DT": 1637550000000,
            "Open": "5225000",
            "Low": "5173000",
            "High": "5234000",
            "Close": "5186000",
            "Volume": "649.3078",
            "Adj_Close": "5186000"
        },
        {
            "DT": 1637553600000,
            "Open": "5186000",
            "Low": "5173000",
            "High": "5211000",
            "Close": "5181000",
            "Volume": "333.5824",
            "Adj_Close": "5181000"
        },
        {
            "DT": 1637557200000,
            "Open": "5179000",
            "Low": "5160000",
            "High": "5208000",
            "Close": "5207000",
            "Volume": "427.6038",
            "Adj_Close": "5207000"
        },
        {
            "DT": 1637560800000,
            "Open": "5205000",
            "Low": "5187000",
            "High": "5213000",
            "Close": "5205000",
            "Volume": "331.0953",
            "Adj_Close": "5205000"
        },
        {
            "DT": 1637564400000,
            "Open": "5207000",
            "Low": "5204000",
            "High": "5241000",
            "Close": "5220000",
            "Volume": "275.1634",
            "Adj_Close": "5220000"
        },
        {
            "DT": 1637568000000,
            "Open": "5217000",
            "Low": "5215000",
            "High": "5241000",
            "Close": "5231000",
            "Volume": "292.5683",
            "Adj_Close": "5231000"
        },
        {
            "DT": 1637571600000,
            "Open": "5234000",
            "Low": "5225000",
            "High": "5269000",
            "Close": "5226000",
            "Volume": "274.7871",
            "Adj_Close": "5226000"
        },
        {
            "DT": 1637575200000,
            "Open": "5227000",
            "Low": "5204000",
            "High": "5242000",
            "Close": "5234000",
            "Volume": "248.9172",
            "Adj_Close": "5234000"
        },
        {
            "DT": 1637578800000,
            "Open": "5235000",
            "Low": "5210000",
            "High": "5248000",
            "Close": "5211000",
            "Volume": "180.7926",
            "Adj_Close": "5211000"
        },
        {
            "DT": 1637582400000,
            "Open": "5211000",
            "Low": "5203000",
            "High": "5258000",
            "Close": "5213000",
            "Volume": "345.3562",
            "Adj_Close": "5213000"
        },
        {
            "DT": 1637586000000,
            "Open": "5213000",
            "Low": "5169000",
            "High": "5350000",
            "Close": "5309000",
            "Volume": "919.8971",
            "Adj_Close": "5309000"
        },
        {
            "DT": 1637589600000,
            "Open": "5310000",
            "Low": "5274000",
            "High": "5329000",
            "Close": "5279000",
            "Volume": "216.2932",
            "Adj_Close": "5279000"
        },
        {
            "DT": 1637593200000,
            "Open": "5279000",
            "Low": "5251000",
            "High": "5288000",
            "Close": "5260000",
            "Volume": "185.3557",
            "Adj_Close": "5260000"
        },
        {
            "DT": 1637596800000,
            "Open": "5260000",
            "Low": "5238000",
            "High": "5271000",
            "Close": "5247000",
            "Volume": "215.2745",
            "Adj_Close": "5247000"
        },
        {
            "DT": 1637600400000,
            "Open": "5253000",
            "Low": "5208000",
            "High": "5257000",
            "Close": "5236000",
            "Volume": "87.2153",
            "Adj_Close": "5236000"
        },
        {
            "DT": 1637604000000,
            "Open": "5236000",
            "Low": "5185000",
            "High": "5240000",
            "Close": "5185000",
            "Volume": "180.5049",
            "Adj_Close": "5185000"
        },
        {
            "DT": 1637607600000,
            "Open": "5187000",
            "Low": "5100000",
            "High": "5215000",
            "Close": "5111000",
            "Volume": "410.6657",
            "Adj_Close": "5111000"
        },
        {
            "DT": 1637611200000,
            "Open": "5111000",
            "Low": "5103000",
            "High": "5143000",
            "Close": "5113000",
            "Volume": "162.5654",
            "Adj_Close": "5113000"
        },
        {
            "DT": 1637614800000,
            "Open": "5110000",
            "Low": "5072000",
            "High": "5129000",
            "Close": "5122000",
            "Volume": "406.9416",
            "Adj_Close": "5122000"
        },
        {
            "DT": 1637618400000,
            "Open": "5119000",
            "Low": "5105000",
            "High": "5148000",
            "Close": "5147000",
            "Volume": "205.0634",
            "Adj_Close": "5147000"
        },
        {
            "DT": 1637622000000,
            "Open": "5147000",
            "Low": "5117000",
            "High": "5157000",
            "Close": "5119000",
            "Volume": "213.8294",
            "Adj_Close": "5119000"
        },
        {
            "DT": 1637625600000,
            "Open": "5117000",
            "Low": "5087000",
            "High": "5171000",
            "Close": "5170000",
            "Volume": "456.1343",
            "Adj_Close": "5170000"
        },
        {
            "DT": 1637629200000,
            "Open": "5171000",
            "Low": "5150000",
            "High": "5194000",
            "Close": "5171000",
            "Volume": "425.6346",
            "Adj_Close": "5171000"
        },
        {
            "DT": 1637632800000,
            "Open": "5170000",
            "Low": "5120000",
            "High": "5170000",
            "Close": "5166000",
            "Volume": "444.756",
            "Adj_Close": "5166000"
        },
        {
            "DT": 1637636400000,
            "Open": "5166000",
            "Low": "5156000",
            "High": "5212000",
            "Close": "5175000",
            "Volume": "492.8214",
            "Adj_Close": "5175000"
        },
        {
            "DT": 1637640000000,
            "Open": "5176000",
            "Low": "5161000",
            "High": "5195000",
            "Close": "5172000",
            "Volume": "369.7507",
            "Adj_Close": "5172000"
        },
        {
            "DT": 1637643600000,
            "Open": "5172000",
            "Low": "5137000",
            "High": "5175000",
            "Close": "5154000",
            "Volume": "443.8407",
            "Adj_Close": "5154000"
        },
        {
            "DT": 1637647200000,
            "Open": "5155000",
            "Low": "5135000",
            "High": "5171000",
            "Close": "5150000",
            "Volume": "284.3847",
            "Adj_Close": "5150000"
        },
        {
            "DT": 1637650800000,
            "Open": "5152000",
            "Low": "5101000",
            "High": "5154000",
            "Close": "5119000",
            "Volume": "377.511",
            "Adj_Close": "5119000"
        },
        {
            "DT": 1637654400000,
            "Open": "5119000",
            "Low": "5097000",
            "High": "5159000",
            "Close": "5146000",
            "Volume": "528.3749",
            "Adj_Close": "5146000"
        },
        {
            "DT": 1637658000000,
            "Open": "5149000",
            "Low": "5104000",
            "High": "5213000",
            "Close": "5175000",
            "Volume": "895.3746",
            "Adj_Close": "5175000"
        },
        {
            "DT": 1637661600000,
            "Open": "5175000",
            "Low": "5153000",
            "High": "5279000",
            "Close": "5183000",
            "Volume": "340.9831",
            "Adj_Close": "5183000"
        },
        {
            "DT": 1637665200000,
            "Open": "5183000",
            "Low": "5155000",
            "High": "5200000",
            "Close": "5171000",
            "Volume": "204.4163",
            "Adj_Close": "5171000"
        },
        {
            "DT": 1637668800000,
            "Open": "5172000",
            "Low": "5169000",
            "High": "5201000",
            "Close": "5180000",
            "Volume": "390.524",
            "Adj_Close": "5180000"
        },
        {
            "DT": 1637672400000,
            "Open": "5179000",
            "Low": "5178000",
            "High": "5227000",
            "Close": "5221000",
            "Volume": "165.8441",
            "Adj_Close": "5221000"
        },
        {
            "DT": 1637676000000,
            "Open": "5218000",
            "Low": "5214000",
            "High": "5360000",
            "Close": "5353000",
            "Volume": "695.6089",
            "Adj_Close": "5353000"
        },
        {
            "DT": 1637679600000,
            "Open": "5355000",
            "Low": "5309000",
            "High": "5376000",
            "Close": "5309000",
            "Volume": "582.5009",
            "Adj_Close": "5309000"
        },
        {
            "DT": 1637683200000,
            "Open": "5312000",
            "Low": "5311000",
            "High": "5413000",
            "Close": "5413000",
            "Volume": "473.7266",
            "Adj_Close": "5413000"
        },
        {
            "DT": 1637686800000,
            "Open": "5412000",
            "Low": "5382000",
            "High": "5415000",
            "Close": "5388000",
            "Volume": "131.7591",
            "Adj_Close": "5388000"
        },
        {
            "DT": 1637690400000,
            "Open": "5386000",
            "Low": "5352000",
            "High": "5395000",
            "Close": "5386000",
            "Volume": "292.3776",
            "Adj_Close": "5386000"
        },
        {
            "DT": 1637694000000,
            "Open": "5386000",
            "Low": "5375000",
            "High": "5422000",
            "Close": "5420000",
            "Volume": "209.2013",
            "Adj_Close": "5420000"
        },
        {
            "DT": 1637697600000,
            "Open": "5422000",
            "Low": "5416000",
            "High": "5450000",
            "Close": "5450000",
            "Volume": "273.8286",
            "Adj_Close": "5450000"
        },
        {
            "DT": 1637701200000,
            "Open": "5449000",
            "Low": "5400000",
            "High": "5449000",
            "Close": "5409000",
            "Volume": "167.5168",
            "Adj_Close": "5409000"
        },
        {
            "DT": 1637704800000,
            "Open": "5409000",
            "Low": "5380000",
            "High": "5413000",
            "Close": "5389000",
            "Volume": "305.6889",
            "Adj_Close": "5389000"
        },
        {
            "DT": 1637708400000,
            "Open": "5391000",
            "Low": "5384000",
            "High": "5413000",
            "Close": "5398000",
            "Volume": "180.4343",
            "Adj_Close": "5398000"
        },
        {
            "DT": 1637712000000,
            "Open": "5399000",
            "Low": "5393000",
            "High": "5437000",
            "Close": "5409000",
            "Volume": "334.352",
            "Adj_Close": "5409000"
        },
        {
            "DT": 1637715600000,
            "Open": "5410000",
            "Low": "5340000",
            "High": "5417000",
            "Close": "5340000",
            "Volume": "255.6556",
            "Adj_Close": "5340000"
        },
        {
            "DT": 1637719200000,
            "Open": "5340000",
            "Low": "5284000",
            "High": "5347000",
            "Close": "5297000",
            "Volume": "286.1127",
            "Adj_Close": "5297000"
        },
        {
            "DT": 1637722800000,
            "Open": "5297000",
            "Low": "5284000",
            "High": "5310000",
            "Close": "5295000",
            "Volume": "156.5721",
            "Adj_Close": "5295000"
        },
        {
            "DT": 1637726400000,
            "Open": "5296000",
            "Low": "5288000",
            "High": "5338000",
            "Close": "5311000",
            "Volume": "284.0861",
            "Adj_Close": "5311000"
        },
        {
            "DT": 1637730000000,
            "Open": "5311000",
            "Low": "5300000",
            "High": "5332000",
            "Close": "5313000",
            "Volume": "427.9442",
            "Adj_Close": "5313000"
        },
        {
            "DT": 1637733600000,
            "Open": "5311000",
            "Low": "5263000",
            "High": "5328000",
            "Close": "5326000",
            "Volume": "337.8758",
            "Adj_Close": "5326000"
        },
        {
            "DT": 1637737200000,
            "Open": "5324000",
            "Low": "5311000",
            "High": "5342000",
            "Close": "5314000",
            "Volume": "225.555",
            "Adj_Close": "5314000"
        },
        {
            "DT": 1637740800000,
            "Open": "5314000",
            "Low": "5311000",
            "High": "5388000",
            "Close": "5361000",
            "Volume": "595.1775",
            "Adj_Close": "5361000"
        },
        {
            "DT": 1637744400000,
            "Open": "5363000",
            "Low": "5336000",
            "High": "5386000",
            "Close": "5360000",
            "Volume": "654.9008",
            "Adj_Close": "5360000"
        },
        {
            "DT": 1637748000000,
            "Open": "5354000",
            "Low": "5311000",
            "High": "5362000",
            "Close": "5311000",
            "Volume": "287.5201",
            "Adj_Close": "5311000"
        },
        {
            "DT": 1637751600000,
            "Open": "5315000",
            "Low": "5312000",
            "High": "5365000",
            "Close": "5356000",
            "Volume": "159.6686",
            "Adj_Close": "5356000"
        },
        {
            "DT": 1637755200000,
            "Open": "5354000",
            "Low": "5336000",
            "High": "5380000",
            "Close": "5345000",
            "Volume": "148.5071",
            "Adj_Close": "5345000"
        },
        {
            "DT": 1637758800000,
            "Open": "5346000",
            "Low": "5288000",
            "High": "5369000",
            "Close": "5300000",
            "Volume": "149.882",
            "Adj_Close": "5300000"
        },
        {
            "DT": 1637762400000,
            "Open": "5299000",
            "Low": "5237000",
            "High": "5320000",
            "Close": "5266000",
            "Volume": "585.8089",
            "Adj_Close": "5266000"
        },
        {
            "DT": 1637766000000,
            "Open": "5266000",
            "Low": "5266000",
            "High": "5266000",
            "Close": "5266000",
            "Volume": "0",
            "Adj_Close": "5266000"
        },
        {
            "DT": 1637769600000,
            "Open": "5266000",
            "Low": "5266000",
            "High": "5266000",
            "Close": "5266000",
            "Volume": "0",
            "Adj_Close": "5266000"
        },
        {
            "DT": 1637773200000,
            "Open": "5268000",
            "Low": "5254000",
            "High": "5296000",
            "Close": "5296000",
            "Volume": "8.8646",
            "Adj_Close": "5296000"
        },
        {
            "DT": 1637776800000,
            "Open": "5276000",
            "Low": "5271000",
            "High": "5335000",
            "Close": "5275000",
            "Volume": "41.9672",
            "Adj_Close": "5275000"
        },
        {
            "DT": 1637780400000,
            "Open": "5286000",
            "Low": "5260000",
            "High": "5301000",
            "Close": "5287000",
            "Volume": "4.7864",
            "Adj_Close": "5287000"
        },
        {
            "DT": 1637784000000,
            "Open": "5287000",
            "Low": "5287000",
            "High": "5367000",
            "Close": "5367000",
            "Volume": "121.4015",
            "Adj_Close": "5367000"
        },
        {
            "DT": 1637787600000,
            "Open": "5368000",
            "Low": "5339000",
            "High": "5388000",
            "Close": "5353000",
            "Volume": "26.5703",
            "Adj_Close": "5353000"
        },
        {
            "DT": 1637791200000,
            "Open": "5358000",
            "Low": "5303000",
            "High": "5363000",
            "Close": "5309000",
            "Volume": "22.0011",
            "Adj_Close": "5309000"
        },
        {
            "DT": 1637794800000,
            "Open": "5313000",
            "Low": "5305000",
            "High": "5353000",
            "Close": "5353000",
            "Volume": "38.601",
            "Adj_Close": "5353000"
        },
        {
            "DT": 1637798400000,
            "Open": "5354000",
            "Low": "5319000",
            "High": "5441000",
            "Close": "5423000",
            "Volume": "257.8492",
            "Adj_Close": "5423000"
        },
        {
            "DT": 1637802000000,
            "Open": "5422000",
            "Low": "5394000",
            "High": "5430000",
            "Close": "5412000",
            "Volume": "70.671",
            "Adj_Close": "5412000"
        },
        {
            "DT": 1637805600000,
            "Open": "5411000",
            "Low": "5377000",
            "High": "5425000",
            "Close": "5404000",
            "Volume": "75.4685",
            "Adj_Close": "5404000"
        },
        {
            "DT": 1637809200000,
            "Open": "5404000",
            "Low": "5393000",
            "High": "5424000",
            "Close": "5403000",
            "Volume": "63.1813",
            "Adj_Close": "5403000"
        },
        {
            "DT": 1637812800000,
            "Open": "5403000",
            "Low": "5351000",
            "High": "5409000",
            "Close": "5357000",
            "Volume": "38.3093",
            "Adj_Close": "5357000"
        },
        {
            "DT": 1637816400000,
            "Open": "5357000",
            "Low": "5326000",
            "High": "5367000",
            "Close": "5350000",
            "Volume": "81.0916",
            "Adj_Close": "5350000"
        },
        {
            "DT": 1637820000000,
            "Open": "5335000",
            "Low": "5319000",
            "High": "5360000",
            "Close": "5319000",
            "Volume": "85.779",
            "Adj_Close": "5319000"
        },
        {
            "DT": 1637823600000,
            "Open": "5352000",
            "Low": "5351000",
            "High": "5394000",
            "Close": "5368000",
            "Volume": "51.5533",
            "Adj_Close": "5368000"
        },
        {
            "DT": 1637827200000,
            "Open": "5369000",
            "Low": "5355000",
            "High": "5398000",
            "Close": "5355000",
            "Volume": "59.1142",
            "Adj_Close": "5355000"
        },
        {
            "DT": 1637830800000,
            "Open": "5355000",
            "Low": "5344000",
            "High": "5360000",
            "Close": "5357000",
            "Volume": "94.0736",
            "Adj_Close": "5357000"
        },
        {
            "DT": 1637834400000,
            "Open": "5358000",
            "Low": "5358000",
            "High": "5476000",
            "Close": "5457000",
            "Volume": "317.5766",
            "Adj_Close": "5457000"
        },
        {
            "DT": 1637838000000,
            "Open": "5458000",
            "Low": "5429000",
            "High": "5480000",
            "Close": "5480000",
            "Volume": "132.9375",
            "Adj_Close": "5480000"
        },
        {
            "DT": 1637841600000,
            "Open": "5480000",
            "Low": "5479000",
            "High": "5578000",
            "Close": "5578000",
            "Volume": "423.2554",
            "Adj_Close": "5578000"
        },
        {
            "DT": 1637845200000,
            "Open": "5578000",
            "Low": "5523000",
            "High": "5588000",
            "Close": "5555000",
            "Volume": "406.1073",
            "Adj_Close": "5555000"
        },
        {
            "DT": 1637848800000,
            "Open": "5555000",
            "Low": "5553000",
            "High": "5598000",
            "Close": "5591000",
            "Volume": "125.4485",
            "Adj_Close": "5591000"
        },
        {
            "DT": 1637852400000,
            "Open": "5591000",
            "Low": "5558000",
            "High": "5612000",
            "Close": "5573000",
            "Volume": "190.2944",
            "Adj_Close": "5573000"
        },
        {
            "DT": 1637856000000,
            "Open": "5574000",
            "Low": "5567000",
            "High": "5617000",
            "Close": "5605000",
            "Volume": "160.7271",
            "Adj_Close": "5605000"
        },
        {
            "DT": 1637859600000,
            "Open": "5604000",
            "Low": "5604000",
            "High": "5643000",
            "Close": "5626000",
            "Volume": "78.7934",
            "Adj_Close": "5626000"
        },
        {
            "DT": 1637863200000,
            "Open": "5627000",
            "Low": "5599000",
            "High": "5635000",
            "Close": "5601000",
            "Volume": "36.005",
            "Adj_Close": "5601000"
        },
        {
            "DT": 1637866800000,
            "Open": "5602000",
            "Low": "5590000",
            "High": "5617000",
            "Close": "5611000",
            "Volume": "44.7574",
            "Adj_Close": "5611000"
        },
        {
            "DT": 1637870400000,
            "Open": "5617000",
            "Low": "5611000",
            "High": "5638000",
            "Close": "5615000",
            "Volume": "49.5616",
            "Adj_Close": "5615000"
        },
        {
            "DT": 1637874000000,
            "Open": "5615000",
            "Low": "5586000",
            "High": "5630000",
            "Close": "5597000",
            "Volume": "40.6241",
            "Adj_Close": "5597000"
        },
        {
            "DT": 1637877600000,
            "Open": "5597000",
            "Low": "5573000",
            "High": "5623000",
            "Close": "5617000",
            "Volume": "111.0375",
            "Adj_Close": "5617000"
        },
        {
            "DT": 1637881200000,
            "Open": "5624000",
            "Low": "5604000",
            "High": "5656000",
            "Close": "5610000",
            "Volume": "250.3618",
            "Adj_Close": "5610000"
        },
        {
            "DT": 1637884800000,
            "Open": "5617000",
            "Low": "5588000",
            "High": "5652000",
            "Close": "5591000",
            "Volume": "108.7284",
            "Adj_Close": "5591000"
        },
        {
            "DT": 1637888400000,
            "Open": "5589000",
            "Low": "5583000",
            "High": "5620000",
            "Close": "5590000",
            "Volume": "92.1633",
            "Adj_Close": "5590000"
        },
        {
            "DT": 1637892000000,
            "Open": "5590000",
            "Low": "5575000",
            "High": "5609000",
            "Close": "5576000",
            "Volume": "140.789",
            "Adj_Close": "5576000"
        },
        {
            "DT": 1637895600000,
            "Open": "5575000",
            "Low": "5546000",
            "High": "5600000",
            "Close": "5550000",
            "Volume": "208.6087",
            "Adj_Close": "5550000"
        },
        {
            "DT": 1637899200000,
            "Open": "5546000",
            "Low": "5525000",
            "High": "5568000",
            "Close": "5547000",
            "Volume": "153.7405",
            "Adj_Close": "5547000"
        },
        {
            "DT": 1637902800000,
            "Open": "5547000",
            "Low": "5507000",
            "High": "5551000",
            "Close": "5539000",
            "Volume": "241.7333",
            "Adj_Close": "5539000"
        },
        {
            "DT": 1637906400000,
            "Open": "5539000",
            "Low": "5526000",
            "High": "5549000",
            "Close": "5536000",
            "Volume": "132.6311",
            "Adj_Close": "5536000"
        },
        {
            "DT": 1637910000000,
            "Open": "5536000",
            "Low": "5450000",
            "High": "5548000",
            "Close": "5488000",
            "Volume": "299.6176",
            "Adj_Close": "5488000"
        },
        {
            "DT": 1637913600000,
            "Open": "5488000",
            "Low": "5147000",
            "High": "5490000",
            "Close": "5251000",
            "Volume": "852.2941",
            "Adj_Close": "5251000"
        },
        {
            "DT": 1637917200000,
            "Open": "5264000",
            "Low": "5200000",
            "High": "5290000",
            "Close": "5211000",
            "Volume": "559.3801",
            "Adj_Close": "5211000"
        },
        {
            "DT": 1637920800000,
            "Open": "5201000",
            "Low": "5150000",
            "High": "5226000",
            "Close": "5188000",
            "Volume": "603.8276",
            "Adj_Close": "5188000"
        },
        {
            "DT": 1637924400000,
            "Open": "5189000",
            "Low": "5135000",
            "High": "5259000",
            "Close": "5137000",
            "Volume": "597.965",
            "Adj_Close": "5137000"
        },
        {
            "DT": 1637928000000,
            "Open": "5139000",
            "Low": "5090000",
            "High": "5207000",
            "Close": "5205000",
            "Volume": "588.7722",
            "Adj_Close": "5205000"
        },
        {
            "DT": 1637931600000,
            "Open": "5205000",
            "Low": "5178000",
            "High": "5255000",
            "Close": "5252000",
            "Volume": "282.1222",
            "Adj_Close": "5252000"
        },
        {
            "DT": 1637935200000,
            "Open": "5255000",
            "Low": "5224000",
            "High": "5290000",
            "Close": "5270000",
            "Volume": "212.5539",
            "Adj_Close": "5270000"
        },
        {
            "DT": 1637938800000,
            "Open": "5270000",
            "Low": "5208000",
            "High": "5270000",
            "Close": "5217000",
            "Volume": "120.1856",
            "Adj_Close": "5217000"
        },
        {
            "DT": 1637942400000,
            "Open": "5213000",
            "Low": "5174000",
            "High": "5241000",
            "Close": "5209000",
            "Volume": "166.5895",
            "Adj_Close": "5209000"
        },
        {
            "DT": 1637946000000,
            "Open": "5209000",
            "Low": "5200000",
            "High": "5249000",
            "Close": "5208000",
            "Volume": "48.3886",
            "Adj_Close": "5208000"
        },
        {
            "DT": 1637949600000,
            "Open": "5206000",
            "Low": "5169000",
            "High": "5206000",
            "Close": "5178000",
            "Volume": "103.717",
            "Adj_Close": "5178000"
        },
        {
            "DT": 1637953200000,
            "Open": "5178000",
            "Low": "5175000",
            "High": "5227000",
            "Close": "5215000",
            "Volume": "86.724",
            "Adj_Close": "5215000"
        },
        {
            "DT": 1637956800000,
            "Open": "5215000",
            "Low": "5196000",
            "High": "5252000",
            "Close": "5246000",
            "Volume": "74.9821",
            "Adj_Close": "5246000"
        },
        {
            "DT": 1637960400000,
            "Open": "5242000",
            "Low": "5206000",
            "High": "5255000",
            "Close": "5206000",
            "Volume": "61.9922",
            "Adj_Close": "5206000"
        },
        {
            "DT": 1637964000000,
            "Open": "5205000",
            "Low": "5170000",
            "High": "5244000",
            "Close": "5175000",
            "Volume": "75.5775",
            "Adj_Close": "5175000"
        },
        {
            "DT": 1637967600000,
            "Open": "5175000",
            "Low": "5122000",
            "High": "5192000",
            "Close": "5151000",
            "Volume": "423.8085",
            "Adj_Close": "5151000"
        },
        {
            "DT": 1637971200000,
            "Open": "5142000",
            "Low": "5115000",
            "High": "5255000",
            "Close": "5213000",
            "Volume": "365.3005",
            "Adj_Close": "5213000"
        },
        {
            "DT": 1637974800000,
            "Open": "5211000",
            "Low": "5185000",
            "High": "5239000",
            "Close": "5232000",
            "Volume": "175.483",
            "Adj_Close": "5232000"
        },
        {
            "DT": 1637978400000,
            "Open": "5232000",
            "Low": "5232000",
            "High": "5284000",
            "Close": "5278000",
            "Volume": "154.4219",
            "Adj_Close": "5278000"
        },
        {
            "DT": 1637982000000,
            "Open": "5280000",
            "Low": "5256000",
            "High": "5298000",
            "Close": "5267000",
            "Volume": "97.7358",
            "Adj_Close": "5267000"
        },
        {
            "DT": 1637985600000,
            "Open": "5257000",
            "Low": "5238000",
            "High": "5273000",
            "Close": "5259000",
            "Volume": "141.5349",
            "Adj_Close": "5259000"
        },
        {
            "DT": 1637989200000,
            "Open": "5260000",
            "Low": "5225000",
            "High": "5265000",
            "Close": "5225000",
            "Volume": "65.336",
            "Adj_Close": "5225000"
        },
        {
            "DT": 1637992800000,
            "Open": "5226000",
            "Low": "5221000",
            "High": "5244000",
            "Close": "5237000",
            "Volume": "44.0105",
            "Adj_Close": "5237000"
        },
        {
            "DT": 1637996400000,
            "Open": "5234000",
            "Low": "5232000",
            "High": "5267000",
            "Close": "5251000",
            "Volume": "84.2523",
            "Adj_Close": "5251000"
        },
        {
            "DT": 1638000000000,
            "Open": "5252000",
            "Low": "5252000",
            "High": "5326000",
            "Close": "5284000",
            "Volume": "91.3886",
            "Adj_Close": "5284000"
        },
        {
            "DT": 1638003600000,
            "Open": "5291000",
            "Low": "5249000",
            "High": "5293000",
            "Close": "5251000",
            "Volume": "49.6757",
            "Adj_Close": "5251000"
        },
        {
            "DT": 1638007200000,
            "Open": "5252000",
            "Low": "5235000",
            "High": "5271000",
            "Close": "5253000",
            "Volume": "37.2087",
            "Adj_Close": "5253000"
        },
        {
            "DT": 1638010800000,
            "Open": "5253000",
            "Low": "5230000",
            "High": "5268000",
            "Close": "5230000",
            "Volume": "79.9865",
            "Adj_Close": "5230000"
        },
        {
            "DT": 1638014400000,
            "Open": "5231000",
            "Low": "5228000",
            "High": "5252000",
            "Close": "5234000",
            "Volume": "44.029",
            "Adj_Close": "5234000"
        },
        {
            "DT": 1638018000000,
            "Open": "5235000",
            "Low": "5230000",
            "High": "5274000",
            "Close": "5251000",
            "Volume": "51.2442",
            "Adj_Close": "5251000"
        },
        {
            "DT": 1638021600000,
            "Open": "5251000",
            "Low": "5245000",
            "High": "5264000",
            "Close": "5249000",
            "Volume": "57.2163",
            "Adj_Close": "5249000"
        }
    ],
    "is_last": false
}